nonebot_plugin_dingzhen/__init__.py
nonebot_plugin_dingzhen/dingzhen.py
nonebot_plugin_dingzhen/example.py
nonebot_plugin_dingzhen-1.2.5.1.dist-info/LICENSE
nonebot_plugin_dingzhen-1.2.5.1.dist-info/METADATA
nonebot_plugin_dingzhen-1.2.5.1.dist-info/WHEEL
nonebot_plugin_dingzhen-1.2.5.1.dist-info/RECORD
