Metadata-Version: 2.3
Name: nonebot_plugin_dingzhen
Version: 1.2.5.1
Summary: 一个为 NoneBot2 提供 QQ 丁真语音生成功能的插件。
License: MIT
Author: Noobie III
Author-email: admin@noobie.top
Requires-Python: >=3.8
Classifier: License :: OSI Approved :: MIT License
Classifier: Programming Language :: Python :: 3
Classifier: Programming Language :: Python :: 3.8
Classifier: Programming Language :: Python :: 3.9
Classifier: Programming Language :: Python :: 3.10
Classifier: Programming Language :: Python :: 3.11
Classifier: Programming Language :: Python :: 3.12
Classifier: Programming Language :: Python :: 3.13
Provides-Extra: dev
Requires-Dist: aiofiles (>=23.1.0)
Requires-Dist: httpx (>=0.24.0)
Requires-Dist: nonebot-adapter-onebot (>=2.3.1)
Requires-Dist: nonebot-plugin-localstore (>=0.7.0)
Requires-Dist: nonebot2 (>=2.3.3)
Requires-Dist: pytest (>=5.2) ; extra == "dev"
